LICENSE
MANIFEST.in
README.md
setup.cfg
setup.py
MACS_virtual_experiment/__init__.py
MACS_virtual_experiment/virtualMACS.py
MACS_virtual_experiment.egg-info/PKG-INFO
MACS_virtual_experiment.egg-info/SOURCES.txt
MACS_virtual_experiment.egg-info/dependency_links.txt
MACS_virtual_experiment.egg-info/requires.txt
MACS_virtual_experiment.egg-info/top_level.txt
MACS_virtual_experiment/.ipynb_checkpoints/Demonstration of Virtual MACS expt object-checkpoint.ipynb
MACS_virtual_experiment/Demonstration/Demonstration of Virtual MACS expt object.ipynb
MACS_virtual_experiment/Demonstration/NaCaNi2F7.lau
MACS_virtual_experiment/Demonstration/TiO2.cif
MACS_virtual_experiment/Demonstration/TiO2.lau
MACS_virtual_experiment/Demonstration/fpx78891.ng0
MACS_virtual_experiment/Demonstration/.ipynb_checkpoints/Demonstration of Virtual MACS expt object-checkpoint.ipynb
MACS_virtual_experiment/Demonstration/Example_ng0_files/fpx78887.ng0
MACS_virtual_experiment/Demonstration/Example_ng0_files/fpx78888.ng0
MACS_virtual_experiment/Demonstration/Example_ng0_files/fpx78889.ng0
MACS_virtual_experiment/Demonstration/Example_ng0_files/fpx78890.ng0
MACS_virtual_experiment/Demonstration/Example_ng0_files/fpx78891.ng0
MACS_virtual_experiment/Demonstration/Example_ng0_files/fpx78892.ng0
MACS_virtual_experiment/Demonstration/Example_ng0_files/fpx78893.ng0
MACS_virtual_experiment/Demonstration/Example_ng0_files/fpx78894.ng0
MACS_virtual_experiment/Demonstration/Example_ng0_files/fpx78895.ng0
MACS_virtual_experiment/Demonstration/Example_ng0_files/fpx78896.ng0
MACS_virtual_experiment/Demonstration/Example_ng0_files/fpx78897.ng0
MACS_virtual_experiment/Demonstration/Example_ng0_files/fpx78898.ng0
MACS_virtual_experiment/Demonstration/Example_ng0_files/fpx78899.ng0
MACS_virtual_experiment/Demonstration/Example_ng0_files/fpx78900.ng0
MACS_virtual_experiment/Demonstration/Example_ng0_files/fpx78901.ng0
MACS_virtual_experiment/Demonstration/Example_ng0_files/fpx78902.ng0
MACS_virtual_experiment/Demonstration/Example_ng0_files/fpx78903.ng0
MACS_virtual_experiment/Demonstration/Simulated ng0 files/tio2_a3scan_cube.ng0
MACS_virtual_experiment/Demonstration/test_experiment/Instrument_files/AF_HB_1D_process.comp
MACS_virtual_experiment/MACS_virtual_experiment.egg-info/PKG-INFO
MACS_virtual_experiment/MACS_virtual_experiment.egg-info/SOURCES.txt
MACS_virtual_experiment/MACS_virtual_experiment.egg-info/dependency_links.txt
MACS_virtual_experiment/MACS_virtual_experiment.egg-info/requires.txt
MACS_virtual_experiment/MACS_virtual_experiment.egg-info/top_level.txt
